gqylpy_import/__init__.py
gqylpy_import/g import.py
gqylpy_import-1.0.dist-info/LICENSE
gqylpy_import-1.0.dist-info/METADATA
gqylpy_import-1.0.dist-info/WHEEL
gqylpy_import-1.0.dist-info/top_level.txt
gqylpy_import-1.0.dist-info/RECORD
